setup.py
mcoll/__init__.py
mcoll/t.py
mcoll/utils.py
mcoll.egg-info/PKG-INFO
mcoll.egg-info/SOURCES.txt
mcoll.egg-info/dependency_links.txt
mcoll.egg-info/not-zip-safe
mcoll.egg-info/top_level.txt