Metadata-Version: 1.0
Name: mcoll
Version: 0.1
Summary: Modern API for python collection
Home-page: https://github.com/nvbn/mcoll
Author: Vladimir Iakovlev
Author-email: nvbn.rm@gmail.com
License: MIT
Platform: UNKNOWN
